{
    "title": {
        "en": "Desire -- Stefania Ferrando",
        "fr": "Désire -- Stefania Ferrando"
    },
    "subject": "",
    "description": {
        "en": "Ferrando is present in the video.",
        "fr": "Ferrando figure dans la restitution de fin de la résidence à Wissous."
    },
    "type": "",
    "source": "",
    "relation": "&source=c00019ba-c822-46ca-bc68-d7c6cbbc6df7&target=79801a83-7782-4f98-b321-83a9d90c6960",
    "coverage": "",
    "creator": "",
    "publisher": "",
    "contributor": "",
    "rights": "",
    "date": "02-20-2023:10:58:52.998817",
    "format": "",
    "identifier": "/Users/jacob/Documents/Git Repos/Spider Webs/COESO-Project/web/edges/1e0d0e4e-a639-4212-b478-bfd45b687410",
    "language": [
        "en",
        "fr"
    ],
    "audience": "",
    "provenance": "",
    "rightsHolder": "",
    "instructionalMethod": "&color=#677691",
    "accrualMethod": "",
    "accrualPeriodicity": "",
    "accrualPolicy": "",
    "uuid": "1e0d0e4e-a639-4212-b478-bfd45b687410",
    "path": "/Users/jacob/Documents/Git Repos/Spider Webs/COESO-Project/web/edges/1e0d0e4e-a639-4212-b478-bfd45b687410",
    "tags": []
}