{
    "title": {
        "en": "Graffione's Intentions -- About the Workshops",
        "fr": "Les intentions de Graffione -- A propos des ateliers"
    },
    "subject": "",
    "description": {
        "en": "Created automatically: \"Graffione\" found in Graffione's Intentions and \"Graffione\" found in About the Workshops.",
        "fr": "Crée automatiquement: \"Graffione\" trouvé dans Les intentions de Graffione et \"Graffione\" trouvé dans A propos des ateliers."
    },
    "type": "",
    "source": "",
    "relation": "&source=6c808962-bcae-42aa-90ad-a0772014de3c&target=f54c4ba0-3e23-4093-aa79-b4212ec7c694",
    "coverage": "",
    "creator": "",
    "publisher": "",
    "contributor": "",
    "rights": "",
    "date": "02-22-2023:14:43:29.964363",
    "format": "",
    "identifier": "/Users/jacob/Documents/Git Repos/Spider Webs/COESO-Project/web/edges/4b3bb913-d147-4eb5-9837-6e184143721a",
    "language": "en",
    "audience": "",
    "provenance": "",
    "rightsHolder": "",
    "instructionalMethod": "",
    "accrualMethod": "",
    "accrualPeriodicity": "",
    "accrualPolicy": "",
    "uuid": "4b3bb913-d147-4eb5-9837-6e184143721a",
    "path": "/Users/jacob/Documents/Git Repos/Spider Webs/COESO-Project/web/edges/4b3bb913-d147-4eb5-9837-6e184143721a",
    "tags": []
}