{
    "title": {
        "en": "Improvised Solos -- Desire and Relationships",
        "fr": "Solos Improvisés -- Le désir et les relations"
    },
    "subject": "",
    "description": {
        "en": "Created automatically: \"Graffione\" found in Improvised Solos and \"Ferrando\" found in Desire and Relationships.",
        "fr": "Crée automatiquement: \"Graffione\" trouvé dans Solos Improvisés et \"Ferrando\" trouvé dans Le désir et les relations."
    },
    "type": "",
    "source": "",
    "relation": "&source=7a9b0199-6acc-4db1-82e8-97139b79594d&target=6f0895f4-df56-4010-9183-1341636d5e38",
    "coverage": "",
    "creator": "",
    "publisher": "",
    "contributor": "",
    "rights": "",
    "date": "02-22-2023:14:43:29.580289",
    "format": "",
    "identifier": "/Users/jacob/Documents/Git Repos/Spider Webs/COESO-Project/web/edges/916db330-a59c-4ffc-b877-08fbe997ad45",
    "language": "en",
    "audience": "",
    "provenance": "",
    "rightsHolder": "",
    "instructionalMethod": "",
    "accrualMethod": "",
    "accrualPeriodicity": "",
    "accrualPolicy": "",
    "uuid": "916db330-a59c-4ffc-b877-08fbe997ad45",
    "path": "/Users/jacob/Documents/Git Repos/Spider Webs/COESO-Project/web/edges/916db330-a59c-4ffc-b877-08fbe997ad45",
    "tags": []
}