{
    "title": {
        "en": "Bologna Workshop (April 2022) -- Alma Ballet Exercises",
        "fr": "Atelier à Bologne (avril 2022) -- Exercises de Alma Ballet"
    },
    "subject": "",
    "description": {
        "en": "The Alma Ballet students were present in Bologna.",
        "fr": "Les étudiants du Alma Ballet ont participé à l'atelier à Bologna."
    },
    "type": "",
    "source": "",
    "relation": "&source=f2a73ea0-d1a4-476a-a2c5-97e429454695&target=c3f92e01-c85a-4487-a40e-6c29f9dc915d",
    "coverage": "",
    "creator": "",
    "publisher": "",
    "contributor": "",
    "rights": "",
    "date": "02-20-2023:10:58:53.057059",
    "format": "",
    "identifier": "/Users/jacob/Documents/Git Repos/Spider Webs/COESO-Project/web/edges/ade361bb-2675-4649-bc23-1497a5116cd4",
    "language": [
        "en",
        "fr"
    ],
    "audience": "",
    "provenance": "",
    "rightsHolder": "",
    "instructionalMethod": "&color=#677691",
    "accrualMethod": "",
    "accrualPeriodicity": "",
    "accrualPolicy": "",
    "uuid": "ade361bb-2675-4649-bc23-1497a5116cd4",
    "path": "/Users/jacob/Documents/Git Repos/Spider Webs/COESO-Project/web/edges/ade361bb-2675-4649-bc23-1497a5116cd4",
    "tags": []
}