{
    "title": {
        "en": "Truth (Ferrando's Description) -- About the Workshops",
        "fr": "Vérité (description de Ferrando) -- A propos des ateliers"
    },
    "subject": "",
    "description": {
        "en": "Created automatically: \"Ferrando\" found in Truth (Ferrando's Description) and \"Graffione\" found in About the Workshops.",
        "fr": "Crée automatiquement: \"Ferrando\" trouvé dans Vérité (description de Ferrando) et \"Graffione\" trouvé dans A propos des ateliers."
    },
    "type": "",
    "source": "",
    "relation": "&source=ec7021d1-0cba-4441-80c2-756c4c510290&target=f54c4ba0-3e23-4093-aa79-b4212ec7c694",
    "coverage": "",
    "creator": "",
    "publisher": "",
    "contributor": "",
    "rights": "",
    "date": "02-22-2023:14:43:32.584355",
    "format": "",
    "identifier": "/Users/jacob/Documents/Git Repos/Spider Webs/COESO-Project/web/edges/008a020a-9d8f-4c76-b0cb-289a272e8175",
    "language": "en",
    "audience": "",
    "provenance": "",
    "rightsHolder": "",
    "instructionalMethod": "",
    "accrualMethod": "",
    "accrualPeriodicity": "",
    "accrualPolicy": "",
    "uuid": "008a020a-9d8f-4c76-b0cb-289a272e8175",
    "path": "/Users/jacob/Documents/Git Repos/Spider Webs/COESO-Project/web/edges/008a020a-9d8f-4c76-b0cb-289a272e8175",
    "tags": []
}