{
    "title": {
        "en": "Cosetta Graffione -- Organic (Graffione's Description)",
        "fr": "Cosetta Graffione -- Organique (description de Graffione)"
    },
    "subject": "",
    "description": {
        "en": "Created automatically: \"Graffione\" found in Cosetta Graffione and \"Graffione\" found in Organic (Graffione's Description).",
        "fr": "Crée automatiquement: \"Graffione\" trouvé dans Cosetta Graffione et \"Graffione\" trouvé dans Organique (description de Graffione)."
    },
    "type": "",
    "source": "",
    "relation": "&source=26c3e8d6-e8c7-4be6-a34c-c56738dee517&target=1546d2c4-9da5-43bd-b109-09bccaf85bb9",
    "coverage": "",
    "creator": "",
    "publisher": "",
    "contributor": "",
    "rights": "",
    "date": "02-22-2023:14:43:31.541823",
    "format": "",
    "identifier": "/Users/jacob/Documents/Git Repos/Spider Webs/COESO-Project/web/edges/ccfee71b-3ff9-431c-82bd-f195c8731ba2",
    "language": "en",
    "audience": "",
    "provenance": "",
    "rightsHolder": "",
    "instructionalMethod": "",
    "accrualMethod": "",
    "accrualPeriodicity": "",
    "accrualPolicy": "",
    "uuid": "ccfee71b-3ff9-431c-82bd-f195c8731ba2",
    "path": "/Users/jacob/Documents/Git Repos/Spider Webs/COESO-Project/web/edges/ccfee71b-3ff9-431c-82bd-f195c8731ba2",
    "tags": []
}