{
    "title": {
        "en": "Desire and Relationships -- Laban Notation - Sober",
        "fr": "Le désir et les relations -- Notation Laban - Sobre"
    },
    "subject": "",
    "description": {
        "en": "Created automatically: \"Ferrando\" found in Desire and Relationships and \"sober\" found in Laban Notation - Sober.",
        "fr": "Crée automatiquement: \"Ferrando\" trouvé dans Le désir et les relations et \"sober\" trouvé dans Notation Laban - Sobre."
    },
    "type": "",
    "source": "",
    "relation": "&source=6f0895f4-df56-4010-9183-1341636d5e38&target=9d22effa-2483-423f-8705-e7affaff7e69",
    "coverage": "",
    "creator": "",
    "publisher": "",
    "contributor": "",
    "rights": "",
    "date": "02-22-2023:14:43:35.191029",
    "format": "",
    "identifier": "/Users/jacob/Documents/Git Repos/Spider Webs/COESO-Project/web/edges/ac372a17-4c49-457a-bb36-5e24004ba283",
    "language": "en",
    "audience": "",
    "provenance": "",
    "rightsHolder": "",
    "instructionalMethod": "",
    "accrualMethod": "",
    "accrualPeriodicity": "",
    "accrualPolicy": "",
    "uuid": "ac372a17-4c49-457a-bb36-5e24004ba283",
    "path": "/Users/jacob/Documents/Git Repos/Spider Webs/COESO-Project/web/edges/ac372a17-4c49-457a-bb36-5e24004ba283",
    "tags": []
}