{
    "title": {
        "en": "Clarisse Bardiot",
        "fr": "Clarisse Bardiot"
    },
    "subject": "",
    "description": {
        "en": "Bardiot participated in the documentation of the pilot.",
        "fr": "Bardiot a patticipé dans la documentation du pilote."
    },
    "type": "",
    "source": "",
    "relation": "",
    "coverage": "",
    "creator": "",
    "publisher": "",
    "contributor": "",
    "rights": "",
    "date": "02-20-2023:09:51:00.863541",
    "format": "&type=document&fileformat=pdf&dimensions-full=595,842&dimensions-region=-1&uri=/Users/jacob/Documents/Git&&_&&Repos/Spider&&_&&Webs/COESO-Project/media/ClarisseBardiot.pdf&pages=1",
    "identifier": "/Users/jacob/Documents/Git Repos/Spider Webs/COESO-Project/web/nodes/74b7d5c6-afa2-46ea-8d5c-e7df809df4ae",
    "language": [
        "en",
        "fr"
    ],
    "audience": "",
    "provenance": "",
    "rightsHolder": "",
    "instructionalMethod": "&color=#358c3e&important=False&annotationPaint=True&annotationOverlay=False&annotationDisplayPos=0,0&annotationDisplayScale=1.0",
    "accrualMethod": "",
    "accrualPeriodicity": "",
    "accrualPolicy": "",
    "uuid": "74b7d5c6-afa2-46ea-8d5c-e7df809df4ae",
    "path": "/Users/jacob/Documents/Git Repos/Spider Webs/COESO-Project/web/nodes/74b7d5c6-afa2-46ea-8d5c-e7df809df4ae",
    "tags": {
        "en": [],
        "fr": []
    }
}