{
    "title": {
        "en": "Laban Notation of a Choregraphic Phrase -- Sober (Ferrando's Description)",
        "fr": "Notation Laban d'une phrase chrorégraphique -- Sobre (description de Ferrando)"
    },
    "subject": "",
    "description": {
        "en": "Created automatically: \"Graffione\" found in Laban Notation of a Choregraphic Phrase and \"Ferrando\" found in Sober (Ferrando's Description).",
        "fr": "Crée automatiquement: \"Graffione\" trouvé dans Notation Laban d'une phrase chrorégraphique et \"Ferrando\" trouvé dans Sobre (description de Ferrando)."
    },
    "type": "",
    "source": "",
    "relation": "&source=a5477008-8331-4318-8df0-c56f478924df&target=f3a6803d-bb69-4121-9a9d-d6a3463f0097",
    "coverage": "",
    "creator": "",
    "publisher": "",
    "contributor": "",
    "rights": "",
    "date": "02-22-2023:14:43:30.625056",
    "format": "",
    "identifier": "/Users/jacob/Documents/Git Repos/Spider Webs/COESO-Project/web/edges/cf7abcd5-5d15-467a-b7e0-c16a0a927d28",
    "language": "en",
    "audience": "",
    "provenance": "",
    "rightsHolder": "",
    "instructionalMethod": "",
    "accrualMethod": "",
    "accrualPeriodicity": "",
    "accrualPolicy": "",
    "uuid": "cf7abcd5-5d15-467a-b7e0-c16a0a927d28",
    "path": "/Users/jacob/Documents/Git Repos/Spider Webs/COESO-Project/web/edges/cf7abcd5-5d15-467a-b7e0-c16a0a927d28",
    "tags": []
}