{
    "title": {
        "en": "COESO Project",
        "fr": "Projet COESO"
    },
    "subject": "",
    "description": {
        "en": "A Horizon 2020 project.",
        "fr": "Un projet Horizon 2020."
    },
    "type": "",
    "source": "",
    "relation": "",
    "coverage": "",
    "creator": "",
    "publisher": "",
    "contributor": "",
    "rights": "",
    "date": "02-20-2023:09:51:00.876057",
    "format": "&type=document&fileformat=pdf&dimensions-full=595,842&dimensions-region=-1&uri=/Users/jacob/Documents/Git&&_&&Repos/Spider&&_&&Webs/COESO-Project/media/COESO_Project.pdf&pages=1",
    "identifier": "/Users/jacob/Documents/Git Repos/Spider Webs/COESO-Project/web/nodes/7fb00960-63e5-4d3e-9128-8351ec537bbd",
    "language": [
        "en",
        "fr"
    ],
    "audience": "",
    "provenance": "",
    "rightsHolder": "",
    "instructionalMethod": "&color=#358c3e&important=False&annotationPaint=True&annotationOverlay=False&annotationDisplayPos=0,0&annotationDisplayScale=1.0",
    "accrualMethod": "",
    "accrualPeriodicity": "",
    "accrualPolicy": "",
    "uuid": "7fb00960-63e5-4d3e-9128-8351ec537bbd",
    "path": "/Users/jacob/Documents/Git Repos/Spider Webs/COESO-Project/web/nodes/7fb00960-63e5-4d3e-9128-8351ec537bbd",
    "tags": {
        "en": [],
        "fr": []
    }
}